bgprocess/__init__.py
bgprocess/constants.py
bgprocess/process.py
bgprocess-1.1.1.dist-info/LICENSE
bgprocess-1.1.1.dist-info/METADATA
bgprocess-1.1.1.dist-info/WHEEL
bgprocess-1.1.1.dist-info/top_level.txt
bgprocess-1.1.1.dist-info/RECORD
