Metadata-Version: 2.1
Name: bgprocess
Version: 1.1.1
Summary: Reads the output of a process line-by-line with a time limit
Home-page: https://github.com/rtmigo/bgprocess_py#bgprocess
Author: Artёm IG
Author-email: ortemeo@gmail.com
License: MIT
Keywords: process,output,timeout
Platform: UNKNOWN
Classifier: Development Status :: 3 - Alpha
Classifier: Intended Audience :: Developers
Classifier: License :: OSI Approved :: MIT License
Classifier: Topic :: Software Development :: Documentation
Classifier: Programming Language :: Python :: 3.6
Classifier: Programming Language :: Python :: 3.7
Classifier: Programming Language :: Python :: 3.8
Classifier: Programming Language :: Python :: 3.9
Classifier: Operating System :: POSIX
Requires-Dist: func-timeout
